{
  "comment": "VECTOR STREAM demo config. scenes: rendered+encoded by gen_scenes.js/encode_scenes.py. sequence: consumed by pack_assets.py. Colors are TED bytes lum<<4|color; attr bytes need bit3 ($08) set for multicolor.",
  "scale": 0.95,
  "angle0": 0.31,
  "scenes": [
    { "name": "cube_t",   "shape": "cube",         "tumble": [1, 1, 0],
      "frames": 80, "scale": 0.72, "move": [1, 2] },
    { "name": "hex_t",    "shape": "hexprism",     "tumble": [1, 1, 0],
      "frames": 80, "scale": 0.7, "move": [1, 1] },
    { "name": "dodeca_t", "shape": "dodecahedron", "tumble": [1, 1, 0],
      "frames": 64, "scale": 0.7, "move": [2, 3] },
    { "name": "mega_dodeca", "shape": "dodecahedron", "tumble": [1, 1, 0],
      "frames": 72, "scale": 1.5, "fx": "fade", "move": [1, 1] }
  ],
  "sequence": [
    { "type": "text",  "ticks": 280, "tune": 0, "border": 0,
      "lines": [["==========================", 6, 7, 14],
                ["LATENT", 9, 17, 1],
                ["PRESENTS", 11, 16, 13],
                ["VECTOR STREAM", 14, 13, 2],
                ["==========================", 17, 7, 14],
                ["3D AT 25 FPS ON A STOCK PLUS/4", 20, 5, 6]],
      "bg": "0x00", "fg": "0x51" },
    { "type": "anim", "scene": "cube_t",  "ticks": 448, "tune": -1, "border": 0,
      "enter": "bottom", "exit": "top",
      "bg": "0x00", "mc1": "0x46", "mc2": "0x6A", "attr": "0x3A" },
    { "type": "anim", "scene": "hex_t", "ticks": 512, "tune": -1, "border": 0,
      "enter": "left", "exit": "right",
      "bg": "0x00", "mc1": "0x45", "mc2": "0x6F", "attr": "0x3A" },
    { "type": "anim", "scene": "cube_t",  "ticks": 448, "tune": -1, "border": 0,
      "enter": "top", "exit": "left",
      "bg": "0x00", "mc1": "0x48", "mc2": "0x67", "attr": "0x3A" },
    { "type": "anim", "scene": "dodeca_t", "ticks": 384, "tune": -1, "border": 0,
      "enter": "right", "exit": "bottom", "musfade": true,
      "bg": "0x00", "mc1": "0x42", "mc2": "0x68", "attr": "0x3A" },
    { "type": "text",  "ticks": 280, "tune": 2, "border": 0, "textfx": true,
      "lines": [["OUT OF THE DARKNESS", 10, 10, 13], ["IT RISES", 14, 16, 2]],
      "bg": "0x00", "fg": "0x51" },
    { "type": "anim", "scene": "mega_dodeca", "ticks": 1536, "tune": -1, "border": 0,
      "bg": "0x00", "mc1": "0x3E", "mc2": "0x56", "attr": "0x46" },
    { "type": "text",  "ticks": 350, "tune": -1, "border": 0,
      "lines": [["VECTOR STREAM", 3, 13, 2],
                ["V10CS CHARACTER STREAMING", 5, 7, 6],
                ["--------------------------", 7, 7, 14],
                ["CODE AND MUSIC", 10, 13, 13],
                ["SPROUT", 12, 17, 1],
                ["HUMAN CRITIC", 15, 13, 13],
                ["BIONIC", 17, 17, 1],
                ["--------------------------", 19, 7, 14],
                ["LATENT 2026", 22, 14, 2]],
      "bg": "0x00", "fg": "0x51" }
  ]
}
